EMO_AI/__init__.py
EMO_AI/_nbdev.py
EMO_AI/all.py
EMO_AI/data_process.py
EMO_AI/from_scratch.py
EMO_AI/label_maps.py
EMO_AI/model_api.py
EMO_AI/tf_model_api.py
EMO_AI/vaplot.py
EMO_AI-0.0.5.dist-info/LICENSE
EMO_AI-0.0.5.dist-info/METADATA
EMO_AI-0.0.5.dist-info/WHEEL
EMO_AI-0.0.5.dist-info/entry_points.txt
EMO_AI-0.0.5.dist-info/top_level.txt
EMO_AI-0.0.5.dist-info/RECORD
