Metadata-Version: 2.1
Name: EMO-AI
Version: 0.0.5
Summary: library for the ai competition, currently private
Home-page: https://github.com/Kelvinthedrugger/EMO_AI/tree/master/
Author: Kelvinthedrugger
Author-email: aangus0628@gmail.com
License: Apache Software License 2.0
Keywords: emotional pointer
Platform: UNKNOWN
Classifier: Development Status :: 3 - Alpha
Classifier: Intended Audience :: Developers
Classifier: Natural Language :: English
Classifier: Programming Language :: Python :: 3.6
Classifier: Programming Language :: Python :: 3.7
Classifier: Programming Language :: Python :: 3.8
Classifier: Programming Language :: Python :: 3.9
Classifier: Programming Language :: Python :: 3.10
Classifier: License :: OSI Approved :: Apache Software License
Requires-Python: >=3.6
License-File: LICENSE
Requires-Dist: pip
Requires-Dist: packaging
Requires-Dist: tokenizers (>=0.12.1)
Requires-Dist: transformers (>=4.18.0)
Provides-Extra: dev
